[
  {
    "OptionName": "Number Of Players",
    "OptionValue": "NumberOfPlayers",
    "OptionFilename": "NumberOfPlayers.json"
  },
  {
    "OptionName": "Difficulty",
    "OptionValue": "DifficultyOptions",
    "OptionFilename": "DifficultyOptions.json"
  },
  {
    "OptionName": "Filter Individual Factions",
    "OptionValue": "FactionFilterMode",
    "OptionFilename": "FactionsList.json"
  },
  {
    "OptionName": "Bonus Options",
    "OptionValue": "BonusOptions",
    "OptionFilename": "BonusOptions.json"
  },
  {
    "OptionName": "Mutators",
    "OptionValue": "MutatorSelector",
    "OptionFilename": "MutatorSelector.json"
  }
]